urbandictionary.py
urbandictionary-1.0.dist-info/DESCRIPTION.rst
urbandictionary-1.0.dist-info/METADATA
urbandictionary-1.0.dist-info/RECORD
urbandictionary-1.0.dist-info/WHEEL
urbandictionary-1.0.dist-info/metadata.json
urbandictionary-1.0.dist-info/top_level.txt
