Metadata-Version: 2.0
Name: urbandictionary
Version: 1.0
Summary: Simple Python wrapper for Urban Dictionary API.
Home-page: https://github.com/bocong/urbandictionary-py
Author: Bocong
Author-email: bocongyin@gmail.com
License: MIT
Keywords: urban dictionary api
Platform: UNKNOWN
Classifier: Development Status :: 4 - Beta
Classifier: Intended Audience :: End Users/Desktop
Classifier: Intended Audience :: Developers
Classifier: License :: OSI Approved :: MIT License
Classifier: Programming Language :: Python :: 2
Classifier: Programming Language :: Python :: 3
